{
    "metadata": {
        "generated_at": "2026-02-15T11:07:13.776645",
        "selected_archetype": "Mix",
        "step_delta": 0.25,
        "horizon": 96
    },
    "environment": {
        "tou_tariff": [
            0.15,
            0.15,
            0.15,
            0.15,
            0.15,
            0.15,
            0.15,
            0.15,
            0.15,
            0.15,
            0.15,
            0.15,
            0.15,
            0.15,
            0.15,
            0.15,
            0.15,
            0.15,
            0.15,
            0.15,
            0.15,
            0.15,
            0.15,
            0.15,
            0.15,
            0.15,
            0.15,
            0.15,
            0.22,
            0.22,
            0.22,
            0.22,
            0.22,
            0.22,
            0.22,
            0.22,
            0.22,
            0.22,
            0.22,
            0.22,
            0.22,
            0.22,
            0.22,
            0.22,
            0.22,
            0.22,
            0.22,
            0.22,
            0.22,
            0.22,
            0.22,
            0.22,
            0.22,
            0.22,
            0.22,
            0.22,
            0.22,
            0.22,
            0.22,
            0.22,
            0.35,
            0.35,
            0.35,
            0.35,
            0.35,
            0.35,
            0.35,
            0.35,
            0.35,
            0.35,
            0.35,
            0.35,
            0.35,
            0.35,
            0.35,
            0.35,
            0.35,
            0.35,
            0.35,
            0.35,
            0.35,
            0.35,
            0.35,
            0.35,
            0.22,
            0.22,
            0.22,
            0.22,
            0.15,
            0.15,
            0.15,
            0.15,
            0.15,
            0.15,
            0.15,
            0.15
        ],
        "pv_forecast": [
            0.0,
            0.0,
            0.0,
            0.0,
            0.0,
            0.0,
            0.0,
            0.0,
            0.0,
            0.0,
            0.0,
            0.0,
            0.0,
            0.0,
            0.0,
            0.0,
            0.0,
            0.0,
            0.0,
            0.0,
            0.0,
            0.0,
            0.0,
            0.0,
            0.0,
            0.7848375507617167,
            1.5663143066406189,
            2.341083864193539,
            3.105828541230249,
            3.857273583637939,
            4.592201188381077,
            5.307464282628015,
            5.999999999999999,
            6.666842796235226,
            7.305137148104648,
            7.912149781200826,
            8.485281374238571,
            9.022077689747729,
            9.520240083494823,
            9.977635347630542,
            10.392304845413264,
            10.76247289839226,
            11.08655439013544,
            11.363161553941268,
            11.59110991546882,
            11.769423364838765,
            11.897338336485724,
            11.97430707886324,
            12.0,
            11.97430707886324,
            11.897338336485724,
            11.769423364838765,
            11.59110991546882,
            11.363161553941268,
            11.086554390135442,
            10.76247289839226,
            10.392304845413264,
            9.977635347630542,
            9.520240083494823,
            9.022077689747729,
            8.485281374238571,
            7.912149781200828,
            7.3051371481046505,
            6.66684279623523,
            5.999999999999999,
            5.30746428262802,
            4.592201188381079,
            3.857273583637941,
            3.1058285412302524,
            2.341083864193538,
            1.5663143066406238,
            0.7848375507617174,
            1.4695761589768238e-15,
            0.0,
            0.0,
            0.0,
            0.0,
            0.0,
            0.0,
            0.0,
            0.0,
            0.0,
            0.0,
            0.0,
            0.0,
            0.0,
            0.0,
            0.0,
            0.0,
            0.0,
            0.0,
            0.0,
            0.0,
            0.0,
            0.0,
            0.0
        ],
        "base_load": [
            5.0,
            5.0,
            5.0,
            5.0,
            5.0,
            5.0,
            5.0,
            5.0,
            5.0,
            5.0,
            5.0,
            5.0,
            5.0,
            5.0,
            5.0,
            5.0,
            5.0,
            5.0,
            5.0,
            5.0,
            5.0,
            5.0,
            5.0,
            5.0,
            5.0,
            5.0,
            5.0,
            5.0,
            5.0,
            5.0,
            5.0,
            5.0,
            5.0,
            5.0,
            5.0,
            5.0,
            10.0,
            10.0,
            10.0,
            10.0,
            10.0,
            10.0,
            10.0,
            10.0,
            10.0,
            10.0,
            10.0,
            10.0,
            10.0,
            10.0,
            10.0,
            10.0,
            10.0,
            10.0,
            10.0,
            10.0,
            10.0,
            10.0,
            10.0,
            10.0,
            10.0,
            10.0,
            10.0,
            10.0,
            10.0,
            10.0,
            10.0,
            10.0,
            5.0,
            5.0,
            5.0,
            5.0,
            5.0,
            5.0,
            5.0,
            5.0,
            5.0,
            5.0,
            5.0,
            5.0,
            5.0,
            5.0,
            5.0,
            5.0,
            5.0,
            5.0,
            5.0,
            5.0,
            5.0,
            5.0,
            5.0,
            5.0,
            5.0,
            5.0,
            5.0,
            5.0
        ]
    },
    "scenarios": {
        "Scenario_A_Baseline": [
            {
                "id": "EV_A_0",
                "arrival": "2026-02-12T09:00:00",
                "departure": "2026-02-12T13:00:00",
                "req_energy": 28.0,
                "init_energy": 8.0,
                "p_max": 11,
                "eff": 0.95,
                "archetype": "Light",
                "priority": "High"
            },
            {
                "id": "EV_A_1",
                "arrival": "2026-02-12T09:15:00",
                "departure": "2026-02-12T13:15:00",
                "req_energy": 52.5,
                "init_energy": 15.0,
                "p_max": 22,
                "eff": 0.92,
                "archetype": "Medium",
                "priority": "High"
            },
            {
                "id": "EV_A_2",
                "arrival": "2026-02-12T09:30:00",
                "departure": "2026-02-12T13:30:00",
                "req_energy": 28.0,
                "init_energy": 8.0,
                "p_max": 11,
                "eff": 0.95,
                "archetype": "Light",
                "priority": "High"
            },
            {
                "id": "EV_A_3",
                "arrival": "2026-02-12T09:45:00",
                "departure": "2026-02-12T13:45:00",
                "req_energy": 52.5,
                "init_energy": 15.0,
                "p_max": 22,
                "eff": 0.92,
                "archetype": "Medium",
                "priority": "High"
            },
            {
                "id": "EV_A_4",
                "arrival": "2026-02-12T10:00:00",
                "departure": "2026-02-12T14:00:00",
                "req_energy": 28.0,
                "init_energy": 8.0,
                "p_max": 11,
                "eff": 0.95,
                "archetype": "Light",
                "priority": "High"
            },
            {
                "id": "EV_A_5",
                "arrival": "2026-02-12T10:15:00",
                "departure": "2026-02-12T14:15:00",
                "req_energy": 52.5,
                "init_energy": 15.0,
                "p_max": 22,
                "eff": 0.92,
                "archetype": "Medium",
                "priority": "Low"
            },
            {
                "id": "EV_A_6",
                "arrival": "2026-02-12T10:30:00",
                "departure": "2026-02-12T14:30:00",
                "req_energy": 28.0,
                "init_energy": 8.0,
                "p_max": 11,
                "eff": 0.95,
                "archetype": "Light",
                "priority": "Low"
            },
            {
                "id": "EV_A_7",
                "arrival": "2026-02-12T10:45:00",
                "departure": "2026-02-12T14:45:00",
                "req_energy": 52.5,
                "init_energy": 15.0,
                "p_max": 22,
                "eff": 0.92,
                "archetype": "Medium",
                "priority": "Low"
            },
            {
                "id": "EV_A_8",
                "arrival": "2026-02-12T09:00:00",
                "departure": "2026-02-12T13:00:00",
                "req_energy": 28.0,
                "init_energy": 8.0,
                "p_max": 11,
                "eff": 0.95,
                "archetype": "Light",
                "priority": "Low"
            },
            {
                "id": "EV_A_9",
                "arrival": "2026-02-12T09:15:00",
                "departure": "2026-02-12T13:15:00",
                "req_energy": 52.5,
                "init_energy": 15.0,
                "p_max": 22,
                "eff": 0.92,
                "archetype": "Medium",
                "priority": "Low"
            },
            {
                "id": "EV_A_10",
                "arrival": "2026-02-12T15:00:00",
                "departure": "2026-02-12T19:00:00",
                "req_energy": 28.0,
                "init_energy": 8.0,
                "p_max": 11,
                "eff": 0.95,
                "archetype": "Light",
                "priority": "High"
            },
            {
                "id": "EV_A_11",
                "arrival": "2026-02-12T15:15:00",
                "departure": "2026-02-12T19:15:00",
                "req_energy": 52.5,
                "init_energy": 15.0,
                "p_max": 22,
                "eff": 0.92,
                "archetype": "Medium",
                "priority": "High"
            },
            {
                "id": "EV_A_12",
                "arrival": "2026-02-12T15:30:00",
                "departure": "2026-02-12T19:30:00",
                "req_energy": 28.0,
                "init_energy": 8.0,
                "p_max": 11,
                "eff": 0.95,
                "archetype": "Light",
                "priority": "High"
            },
            {
                "id": "EV_A_13",
                "arrival": "2026-02-12T15:45:00",
                "departure": "2026-02-12T19:45:00",
                "req_energy": 52.5,
                "init_energy": 15.0,
                "p_max": 22,
                "eff": 0.92,
                "archetype": "Medium",
                "priority": "Low"
            },
            {
                "id": "EV_A_14",
                "arrival": "2026-02-12T15:00:00",
                "departure": "2026-02-12T19:00:00",
                "req_energy": 28.0,
                "init_energy": 8.0,
                "p_max": 11,
                "eff": 0.95,
                "archetype": "Light",
                "priority": "Low"
            },
            {
                "id": "EV_A_15",
                "arrival": "2026-02-12T15:15:00",
                "departure": "2026-02-12T19:15:00",
                "req_energy": 52.5,
                "init_energy": 15.0,
                "p_max": 22,
                "eff": 0.92,
                "archetype": "Medium",
                "priority": "Low"
            }
        ],
        "Scenario_B_MidDayRush": [
            {
                "id": "EV_B_0",
                "arrival": "2026-02-12T08:00:00",
                "departure": "2026-02-12T14:00:00",
                "req_energy": 24.0,
                "init_energy": 4.0,
                "p_max": 11,
                "eff": 0.95,
                "archetype": "Light",
                "priority": "Low"
            },
            {
                "id": "EV_B_1",
                "arrival": "2026-02-12T08:15:00",
                "departure": "2026-02-12T14:15:00",
                "req_energy": 45.0,
                "init_energy": 7.5,
                "p_max": 22,
                "eff": 0.92,
                "archetype": "Medium",
                "priority": "Low"
            },
            {
                "id": "EV_B_2",
                "arrival": "2026-02-12T08:30:00",
                "departure": "2026-02-12T14:30:00",
                "req_energy": 24.0,
                "init_energy": 4.0,
                "p_max": 11,
                "eff": 0.95,
                "archetype": "Light",
                "priority": "Low"
            },
            {
                "id": "EV_B_3",
                "arrival": "2026-02-12T08:45:00",
                "departure": "2026-02-12T14:45:00",
                "req_energy": 45.0,
                "init_energy": 7.5,
                "p_max": 22,
                "eff": 0.92,
                "archetype": "Medium",
                "priority": "Low"
            },
            {
                "id": "EV_B_4",
                "arrival": "2026-02-12T09:00:00",
                "departure": "2026-02-12T15:00:00",
                "req_energy": 24.0,
                "init_energy": 4.0,
                "p_max": 11,
                "eff": 0.95,
                "archetype": "Light",
                "priority": "Low"
            },
            {
                "id": "EV_B_5",
                "arrival": "2026-02-12T12:00:00",
                "departure": "2026-02-12T14:00:00",
                "req_energy": 45.0,
                "init_energy": 7.5,
                "p_max": 22,
                "eff": 0.92,
                "archetype": "Medium",
                "priority": "High"
            },
            {
                "id": "EV_B_6",
                "arrival": "2026-02-12T12:00:00",
                "departure": "2026-02-12T14:00:00",
                "req_energy": 24.0,
                "init_energy": 4.0,
                "p_max": 11,
                "eff": 0.95,
                "archetype": "Light",
                "priority": "High"
            },
            {
                "id": "EV_B_7",
                "arrival": "2026-02-12T12:00:00",
                "departure": "2026-02-12T14:00:00",
                "req_energy": 45.0,
                "init_energy": 7.5,
                "p_max": 22,
                "eff": 0.92,
                "archetype": "Medium",
                "priority": "High"
            },
            {
                "id": "EV_B_8",
                "arrival": "2026-02-12T12:00:00",
                "departure": "2026-02-12T14:00:00",
                "req_energy": 24.0,
                "init_energy": 4.0,
                "p_max": 11,
                "eff": 0.95,
                "archetype": "Light",
                "priority": "High"
            },
            {
                "id": "EV_B_9",
                "arrival": "2026-02-12T12:00:00",
                "departure": "2026-02-12T14:00:00",
                "req_energy": 45.0,
                "init_energy": 7.5,
                "p_max": 22,
                "eff": 0.92,
                "archetype": "Medium",
                "priority": "High"
            },
            {
                "id": "EV_B_10",
                "arrival": "2026-02-12T12:00:00",
                "departure": "2026-02-12T14:00:00",
                "req_energy": 24.0,
                "init_energy": 4.0,
                "p_max": 11,
                "eff": 0.95,
                "archetype": "Light",
                "priority": "High"
            },
            {
                "id": "EV_B_11",
                "arrival": "2026-02-12T12:00:00",
                "departure": "2026-02-12T14:00:00",
                "req_energy": 45.0,
                "init_energy": 7.5,
                "p_max": 22,
                "eff": 0.92,
                "archetype": "Medium",
                "priority": "High"
            },
            {
                "id": "EV_B_12",
                "arrival": "2026-02-12T12:00:00",
                "departure": "2026-02-12T14:00:00",
                "req_energy": 24.0,
                "init_energy": 4.0,
                "p_max": 11,
                "eff": 0.95,
                "archetype": "Light",
                "priority": "High"
            },
            {
                "id": "EV_B_13",
                "arrival": "2026-02-12T12:00:00",
                "departure": "2026-02-12T14:00:00",
                "req_energy": 45.0,
                "init_energy": 7.5,
                "p_max": 22,
                "eff": 0.92,
                "archetype": "Medium",
                "priority": "High"
            },
            {
                "id": "EV_B_14",
                "arrival": "2026-02-12T12:00:00",
                "departure": "2026-02-12T14:00:00",
                "req_energy": 24.0,
                "init_energy": 4.0,
                "p_max": 11,
                "eff": 0.95,
                "archetype": "Light",
                "priority": "High"
            }
        ],
        "Scenario_C_LateReturn": [
            {
                "id": "EV_C_0",
                "arrival": "2026-02-12T14:00:00",
                "departure": "2026-02-12T16:45:21.531100",
                "req_energy": 28.0,
                "init_energy": 4.0,
                "p_max": 11,
                "eff": 0.95,
                "archetype": "Light",
                "priority": "High"
            },
            {
                "id": "EV_C_1",
                "arrival": "2026-02-12T14:00:00",
                "departure": "2026-02-12T16:40:04.743083",
                "req_energy": 52.5,
                "init_energy": 7.5,
                "p_max": 22,
                "eff": 0.92,
                "archetype": "Medium",
                "priority": "High"
            },
            {
                "id": "EV_C_2",
                "arrival": "2026-02-12T14:00:00",
                "departure": "2026-02-12T16:45:21.531100",
                "req_energy": 28.0,
                "init_energy": 4.0,
                "p_max": 11,
                "eff": 0.95,
                "archetype": "Light",
                "priority": "High"
            },
            {
                "id": "EV_C_3",
                "arrival": "2026-02-12T14:00:00",
                "departure": "2026-02-12T16:40:04.743083",
                "req_energy": 52.5,
                "init_energy": 7.5,
                "p_max": 22,
                "eff": 0.92,
                "archetype": "Medium",
                "priority": "High"
            },
            {
                "id": "EV_C_4",
                "arrival": "2026-02-12T14:00:00",
                "departure": "2026-02-12T16:45:21.531100",
                "req_energy": 28.0,
                "init_energy": 4.0,
                "p_max": 11,
                "eff": 0.95,
                "archetype": "Light",
                "priority": "High"
            },
            {
                "id": "EV_C_5",
                "arrival": "2026-02-12T14:00:00",
                "departure": "2026-02-12T16:40:04.743083",
                "req_energy": 52.5,
                "init_energy": 7.5,
                "p_max": 22,
                "eff": 0.92,
                "archetype": "Medium",
                "priority": "High"
            },
            {
                "id": "EV_C_6",
                "arrival": "2026-02-12T14:00:00",
                "departure": "2026-02-12T16:45:21.531100",
                "req_energy": 28.0,
                "init_energy": 4.0,
                "p_max": 11,
                "eff": 0.95,
                "archetype": "Light",
                "priority": "High"
            },
            {
                "id": "EV_C_7",
                "arrival": "2026-02-12T14:00:00",
                "departure": "2026-02-12T16:40:04.743083",
                "req_energy": 52.5,
                "init_energy": 7.5,
                "p_max": 22,
                "eff": 0.92,
                "archetype": "Medium",
                "priority": "High"
            }
        ]
    }
}